README.txt
setup.py
whatsup.ini
whatsup/__init__.py
whatsup/factory.py
whatsup/whatsup.py
whatsup.egg-info/PKG-INFO
whatsup.egg-info/SOURCES.txt
whatsup.egg-info/dependency_links.txt
whatsup.egg-info/entry_points.txt
whatsup.egg-info/not-zip-safe
whatsup.egg-info/requires.txt
whatsup.egg-info/top_level.txt
whatsup/static/css/tripoli.base.css
whatsup/static/css/tripoli.base.ie.css
whatsup/static/css/whatsup.css
whatsup/static/img/transparent.gif
whatsup/static/js/jquery.js
whatsup/templates/contact.html
whatsup/templates/contacts.html
whatsup/templates/fixed.html
whatsup/templates/index.html
whatsup/templates/outage.html
whatsup/templates/site.html