Metadata-Version: 1.0
Name: whatsup
Version: 0.1.1
Summary: Outage Escalation Tool and Site Contact Info
Home-page: https://projects.openplans.org/whatsup
Author: Chris Patterson and Jeff Hammel
Author-email: jhammel@openplans.org
License: GPL
Platform: UNKNOWN
